text_machina/__init__.py
text_machina/cli.py
text_machina/cli_utils.py
text_machina/version.py
text_machina/src/__init__.py
text_machina/src/config.py
text_machina/src/data.py
text_machina/src/postprocessing.py
text_machina/src/types.py
text_machina/src/common/__init__.py
text_machina/src/common/exceptions.py
text_machina/src/common/logging.py
text_machina/src/common/utils.py
text_machina/src/constrainers/__init__.py
text_machina/src/constrainers/base.py
text_machina/src/constrainers/length.py
text_machina/src/exploration/__init__.py
text_machina/src/exploration/attribution.py
text_machina/src/exploration/base.py
text_machina/src/exploration/boundary.py
text_machina/src/exploration/detection.py
text_machina/src/exploration/mixcase.py
text_machina/src/extractors/__init__.py
text_machina/src/extractors/auxiliary.py
text_machina/src/extractors/base.py
text_machina/src/extractors/combined.py
text_machina/src/extractors/dummy.py
text_machina/src/extractors/entity_list.py
text_machina/src/extractors/example.py
text_machina/src/extractors/noun_list.py
text_machina/src/extractors/sentence_gap.py
text_machina/src/extractors/sentence_masking.py
text_machina/src/extractors/sentence_prefix.py
text_machina/src/extractors/sentence_rewriting.py
text_machina/src/extractors/types.py
text_machina/src/extractors/utils.py
text_machina/src/extractors/word_gap.py
text_machina/src/extractors/word_masking.py
text_machina/src/extractors/word_prefix.py
text_machina/src/generators/__init__.py
text_machina/src/generators/attribution.py
text_machina/src/generators/base.py
text_machina/src/generators/boundary.py
text_machina/src/generators/detection.py
text_machina/src/generators/mixcase.py
text_machina/src/metrics/__init__.py
text_machina/src/metrics/base.py
text_machina/src/metrics/mauve.py
text_machina/src/metrics/perplexity.py
text_machina/src/metrics/repetition_diversity.py
text_machina/src/metrics/simple_model.py
text_machina/src/metrics/token_classification.py
text_machina-0.2.12.dist-info/LICENSE
text_machina-0.2.12.dist-info/METADATA
text_machina-0.2.12.dist-info/WHEEL
text_machina-0.2.12.dist-info/entry_points.txt
text_machina-0.2.12.dist-info/top_level.txt
text_machina-0.2.12.dist-info/RECORD
