Metadata-Version: 2.1
Name: text-machina
Version: 0.2.12
Summary: Text Machina: Seamless Generation of Machine-Generated Text Datasets
Home-page: https://github.com/Genaios/TextMachina
Author: Genaios
Classifier: Development Status :: 4 - Beta
Classifier: Environment :: Console
Classifier: Intended Audience :: Developers
Classifier: Topic :: Scientific/Engineering :: Artificial Intelligence
Classifier: License :: Other/Proprietary License
Classifier: Programming Language :: Python :: 3 :: Only
Classifier: Operating System :: MacOS :: MacOS X
Classifier: Operating System :: Microsoft :: Windows
Classifier: Operating System :: POSIX
Requires-Python: >=3.8.0
License-File: LICENSE
Requires-Dist: scipy >=1.10.1
Requires-Dist: PyYAML >=6.0.1
Requires-Dist: datasets >=2.14.4
Requires-Dist: spacy >=3.6.1
Requires-Dist: typer >=0.9.0
Requires-Dist: pydantic >=2.3.0
Requires-Dist: petname >=2.6
Requires-Dist: pycountry >=22.3.5
Requires-Dist: ftfy >=6.1.3
Requires-Dist: fasttext-wheel
Requires-Dist: rich >=13.7.0
Requires-Dist: scikit-learn >=1.3.2
Requires-Dist: mauve-text >=0.3.0
Requires-Dist: matplotlib >=3.7.4
Requires-Dist: tabulate >=0.9.0
Requires-Dist: readchar >=4.0.5
Requires-Dist: evaluate >=0.4.1
Requires-Dist: textstat >=0.7.3
Requires-Dist: seqeval >=1.2.2
Provides-Extra: ai21
Requires-Dist: ai21 >=2.0.0 ; extra == 'ai21'
Requires-Dist: ai21-tokenizer >=0.3.11 ; extra == 'ai21'
Provides-Extra: all
Requires-Dist: openai >=1 ; extra == 'all'
Requires-Dist: tiktoken >=0.4.0 ; extra == 'all'
Requires-Dist: boto3 ; extra == 'all'
Requires-Dist: ai21 >=2.0.0 ; extra == 'all'
Requires-Dist: ai21-tokenizer >=0.3.11 ; extra == 'all'
Requires-Dist: anthropic >=0.7.2 ; extra == 'all'
Requires-Dist: cohere >=4.36 ; extra == 'all'
Requires-Dist: torch ==2.0.1 ; extra == 'all'
Requires-Dist: transformers >=4.32.0 ; extra == 'all'
Requires-Dist: accelerate >=0.22.0 ; extra == 'all'
Requires-Dist: bitsandbytes >=0.41.1 ; extra == 'all'
Requires-Dist: requests >=2.31.0 ; extra == 'all'
Requires-Dist: google-auth ; extra == 'all'
Requires-Dist: google-cloud-aiplatform ==1.25.0 ; extra == 'all'
Provides-Extra: anthropic
Requires-Dist: anthropic >=0.7.2 ; extra == 'anthropic'
Provides-Extra: azure_openai
Requires-Dist: openai >=1 ; extra == 'azure_openai'
Requires-Dist: tiktoken >=0.4.0 ; extra == 'azure_openai'
Provides-Extra: bedrock
Requires-Dist: boto3 ; extra == 'bedrock'
Requires-Dist: tiktoken >=0.4.0 ; extra == 'bedrock'
Provides-Extra: cohere
Requires-Dist: cohere >=4.36 ; extra == 'cohere'
Provides-Extra: dev
Requires-Dist: openai >=1 ; extra == 'dev'
Requires-Dist: tiktoken >=0.4.0 ; extra == 'dev'
Requires-Dist: boto3 ; extra == 'dev'
Requires-Dist: ai21 >=2.0.0 ; extra == 'dev'
Requires-Dist: ai21-tokenizer >=0.3.11 ; extra == 'dev'
Requires-Dist: anthropic >=0.7.2 ; extra == 'dev'
Requires-Dist: cohere >=4.36 ; extra == 'dev'
Requires-Dist: torch ==2.0.1 ; extra == 'dev'
Requires-Dist: transformers >=4.32.0 ; extra == 'dev'
Requires-Dist: accelerate >=0.22.0 ; extra == 'dev'
Requires-Dist: bitsandbytes >=0.41.1 ; extra == 'dev'
Requires-Dist: requests >=2.31.0 ; extra == 'dev'
Requires-Dist: google-auth ; extra == 'dev'
Requires-Dist: google-cloud-aiplatform ==1.25.0 ; extra == 'dev'
Requires-Dist: black ; extra == 'dev'
Requires-Dist: flake8 ; extra == 'dev'
Requires-Dist: mypy ; extra == 'dev'
Requires-Dist: types-requests ; extra == 'dev'
Requires-Dist: pytest ; extra == 'dev'
Requires-Dist: isort ; extra == 'dev'
Requires-Dist: autoflake ; extra == 'dev'
Requires-Dist: pre-commit ; extra == 'dev'
Requires-Dist: pytest-sphinx ; extra == 'dev'
Requires-Dist: pytest-cov ; extra == 'dev'
Requires-Dist: ruff ; extra == 'dev'
Requires-Dist: Sphinx <7.1.0,>=4.3.0 ; extra == 'dev'
Requires-Dist: furo ==2023.7.26 ; extra == 'dev'
Requires-Dist: myst-parser <2.1,>=1.0 ; extra == 'dev'
Requires-Dist: sphinx-copybutton ==0.5.2 ; extra == 'dev'
Requires-Dist: sphinx-autobuild ==2021.3.14 ; extra == 'dev'
Requires-Dist: sphinx-autodoc-typehints ==1.23.3 ; extra == 'dev'
Requires-Dist: packaging ; extra == 'dev'
Requires-Dist: setuptools ; extra == 'dev'
Requires-Dist: build ; extra == 'dev'
Requires-Dist: wheel ; extra == 'dev'
Provides-Extra: huggingface-local
Requires-Dist: torch ==2.0.1 ; extra == 'huggingface-local'
Requires-Dist: transformers >=4.32.0 ; extra == 'huggingface-local'
Requires-Dist: accelerate >=0.22.0 ; extra == 'huggingface-local'
Requires-Dist: bitsandbytes >=0.41.1 ; extra == 'huggingface-local'
Provides-Extra: huggingface-remote
Requires-Dist: requests >=2.31.0 ; extra == 'huggingface-remote'
Provides-Extra: openai
Requires-Dist: openai >=1 ; extra == 'openai'
Requires-Dist: tiktoken >=0.4.0 ; extra == 'openai'
Provides-Extra: vertex
Requires-Dist: google-auth ; extra == 'vertex'
Requires-Dist: google-cloud-aiplatform ==1.25.0 ; extra == 'vertex'
Requires-Dist: tiktoken >=0.4.0 ; extra == 'vertex'
